Metadata-Version: 2.1
Name: dronedesktopnotifier
Version: 0.4
Summary: Get notified on your desktop when your drone.io build finishes.
Home-page: https://github.com/AlxndrJhn/drone-desktop-notifier
Author: Alexander Jahn
Author-email: jahn.alexander@gmail.com
License: GNU GPLv3
Download-URL: https://github.com/AlxndrJhn/drone-desktop-notifier/archive/0.4.tar.gz
Keywords: drone.io,notification,drone,notifier
Platform: UNKNOWN
Classifier: Development Status :: 4 - Beta
Classifier: Intended Audience :: Developers
Classifier: Topic :: Utilities
Classifier: License :: OSI Approved :: GNU General Public License v3 or later (GPLv3+)
Classifier: Programming Language :: Python :: 3.6
Classifier: Programming Language :: Python :: 3.7
